endstone_easybackuper/__init__.py
endstone_easybackuper/easybackuper_plugin.py
endstone_easybackuper-0.4.1.dist-info/METADATA
endstone_easybackuper-0.4.1.dist-info/WHEEL
endstone_easybackuper-0.4.1.dist-info/entry_points.txt
endstone_easybackuper-0.4.1.dist-info/licenses/LICENSE
endstone_easybackuper-0.4.1.dist-info/RECORD
