Metadata-Version: 2.4
Name: endstone-easybackuper
Version: 0.4.1
Summary: 基于 EndStone 的最最最简单的Python热备份插件 / The simplest Python hot backup plugin based on EndStone.
Project-URL: Homepage, https://github.com/MengHanLOVE1027/endstone-easybackuper
Author-email: MengHanLOVE <2193438288@qq.com>
License:                     GNU AFFERO GENERAL PUBLIC LICENSE
License-File: LICENSE
Keywords: backup,endstone,plugins
